Edgar13F/__init__.py
Edgar13F/scraper.py
Edgar13F-0.2.0.dist-info/LICENSE
Edgar13F-0.2.0.dist-info/METADATA
Edgar13F-0.2.0.dist-info/WHEEL
Edgar13F-0.2.0.dist-info/top_level.txt
Edgar13F-0.2.0.dist-info/RECORD
