Metadata-Version: 2.1
Name: Edgar13F
Version: 0.2.0
Summary: A Python package for scraping 13F filings from the SEC Edgar database.
Home-page: https://pypi.org/project/Edgar13F/
Author: Jack Brown
Author-email: jackabrown21@gmail.com
License-File: LICENSE
Requires-Dist: requests
Requires-Dist: beautifulsoup4
Requires-Dist: python-dotenv
